py_log_mjk/__init__.py
py_log_mjk/config_logging.py
py_log_mjk/filters.py
py_log_mjk/formatter.py
py_log_mjk/handler.py
py_log_mjk/main.py
py_log_mjk/settings.py
py_log_mjk/templates/__init__.py
py_log_mjk/templates/default_logging.conf.json
py_log_mjk-0.1.4.dist-info/LICENSE
py_log_mjk-0.1.4.dist-info/METADATA
py_log_mjk-0.1.4.dist-info/WHEEL
py_log_mjk-0.1.4.dist-info/RECORD
