Metadata-Version: 2.3
Name: py_log_mjk
Version: 0.1.4
Summary: Um pacote de logging completo e profissional para aplicações Python.
License: MIT
Keywords: python,logging,toolkit,log,logging-library
Author: Mauricio Araujo
Author-email: mjk_araujo@hotmail.com
Requires-Python: >=3.12
Classifier: Programming Language :: Python :: 3
Classifier: License :: OSI Approved :: MIT License
Classifier: Operating System :: OS Independent
Classifier: Intended Audience :: Developers
Classifier: Topic :: Software Development :: Libraries :: Python Modules
Classifier: Topic :: System :: Logging
Requires-Dist: python-dotenv (>=1.0.1,<2.0.0)
Requires-Dist: rich (>=13.7.1,<14.0.0)
Requires-Dist: setuptools (>=80.9.0,<81.0.0)
Requires-Dist: tzdata (>=2025.2,<2026.0)
